{ "compressionlevel":-1,
 "height":7,
 "infinite":false,
 "layers":[
        {
         "draworder":"topdown",
         "id":2,
         "name":"SPikes",
         "objects":[],
         "opacity":1,
         "type":"objectgroup",
         "visible":true,
         "x":0,
         "y":0
        }, 
        {
         "data":[0, 0, 0, 0, 0, 0, 0, 0, 0, 0, 0, 0, 0, 0, 0, 0, 0, 0, 0, 0, 0, 0, 0, 0, 0, 0, 0, 0, 0, 0, 0, 47, 0, 71, 47, 0, 0, 0, 0, 0, 0, 0, 0, 0, 47, 47, 71, 47, 47, 0, 0, 0, 0, 0, 0, 76, 1, 1, 1, 1, 1, 1, 1, 1, 1, 0, 0, 1, 1, 1, 4, 4, 4, 4, 4, 4, 4, 4, 4, 71, 71, 4, 4, 4, 4, 4, 4, 4, 4, 4, 4, 4, 4, 4, 4, 4, 4, 4],
         "height":7,
         "id":4,
         "name":"Platforms",
         "opacity":1,
         "type":"tilelayer",
         "visible":true,
         "width":14,
         "x":0,
         "y":0
        }],
 "nextlayerid":5,
 "nextobjectid":1,
 "orientation":"orthogonal",
 "renderorder":"right-down",
 "tiledversion":"1.8.1",
 "tileheight":64,
 "tilesets":[
        {
         "firstgid":1,
         "source":"..\/..\/..\/..\/..\/..\/Phaser.tsx"
        }],
 "tilewidth":64,
 "type":"map",
 "version":"1.8",
 "width":14
}